tonereader/__init__.py
tonereader/__main__.py
tonereader/_version.py
tonereader/tonereader.py
tonereader/data/ngram_notsarcastic_count_2.csv
tonereader/data/ngram_notsarcastic_count_3.csv
tonereader/data/ngram_prev_notsarcastic_count_2.csv
tonereader/data/ngram_prev_notsarcastic_count_3.csv
tonereader/data/ngram_prev_sarcastic_count_2.csv
tonereader/data/ngram_prev_sarcastic_count_3.csv
tonereader/data/ngram_sarcastic_count_2.csv
tonereader/data/ngram_sarcastic_count_3.csv
tonereader/data/task_A_En_test.csv
tonereader/tests/test_all.py
tonereader-0.1.3.dist-info/LICENSE
tonereader-0.1.3.dist-info/METADATA
tonereader-0.1.3.dist-info/WHEEL
tonereader-0.1.3.dist-info/top_level.txt
tonereader-0.1.3.dist-info/RECORD
